odoo8_addon_purchase_sale_inter_company-8.0.1.0.0.99.dev22-py2.7-nspkg.pth
odoo8_addon_purchase_sale_inter_company-8.0.1.0.0.99.dev22.dist-info/DESCRIPTION.rst
odoo8_addon_purchase_sale_inter_company-8.0.1.0.0.99.dev22.dist-info/METADATA
odoo8_addon_purchase_sale_inter_company-8.0.1.0.0.99.dev22.dist-info/RECORD
odoo8_addon_purchase_sale_inter_company-8.0.1.0.0.99.dev22.dist-info/WHEEL
odoo8_addon_purchase_sale_inter_company-8.0.1.0.0.99.dev22.dist-info/metadata.json
odoo8_addon_purchase_sale_inter_company-8.0.1.0.0.99.dev22.dist-info/namespace_packages.txt
odoo8_addon_purchase_sale_inter_company-8.0.1.0.0.99.dev22.dist-info/top_level.txt
odoo_addons/purchase_sale_inter_company/README.rst
odoo_addons/purchase_sale_inter_company/__init__.py
odoo_addons/purchase_sale_inter_company/__openerp__.py
odoo_addons/purchase_sale_inter_company/demo/inter_company_purchase_sale.xml
odoo_addons/purchase_sale_inter_company/i18n/de.po
odoo_addons/purchase_sale_inter_company/i18n/es.po
odoo_addons/purchase_sale_inter_company/i18n/fr.po
odoo_addons/purchase_sale_inter_company/i18n/fr_FR.po
odoo_addons/purchase_sale_inter_company/i18n/purchase_sale_inter_company.pot
odoo_addons/purchase_sale_inter_company/i18n/sl.po
odoo_addons/purchase_sale_inter_company/models/__init__.py
odoo_addons/purchase_sale_inter_company/models/account_invoice.py
odoo_addons/purchase_sale_inter_company/models/purchase_order.py
odoo_addons/purchase_sale_inter_company/models/res_company.py
odoo_addons/purchase_sale_inter_company/models/res_config.py
odoo_addons/purchase_sale_inter_company/models/sale_order.py
odoo_addons/purchase_sale_inter_company/static/description/icon.png
odoo_addons/purchase_sale_inter_company/tests/__init__.py
odoo_addons/purchase_sale_inter_company/tests/test_inter_company_purchase_sale.py
odoo_addons/purchase_sale_inter_company/views/purchase_order_view.xml
odoo_addons/purchase_sale_inter_company/views/res_company_view.xml
odoo_addons/purchase_sale_inter_company/views/res_config_view.xml
